wbw/__init__.py
wbw/wbw.py
WBWGenerator-0.0.8.dist-info/METADATA
WBWGenerator-0.0.8.dist-info/WHEEL
WBWGenerator-0.0.8.dist-info/top_level.txt
WBWGenerator-0.0.8.dist-info/RECORD
